datasette_auth_passwords/__init__.py
datasette_auth_passwords/utils.py
datasette_auth_passwords/templates/password_login.html
datasette_auth_passwords/templates/password_tool.html
datasette_auth_passwords-1.1.1.dist-info/METADATA
datasette_auth_passwords-1.1.1.dist-info/WHEEL
datasette_auth_passwords-1.1.1.dist-info/entry_points.txt
datasette_auth_passwords-1.1.1.dist-info/top_level.txt
datasette_auth_passwords-1.1.1.dist-info/RECORD
