Metadata-Version: 2.1
Name: datasette-auth-passwords
Version: 1.1.1
Summary: Datasette plugin for authenticating access using passwords
Home-page: https://github.com/simonw/datasette-auth-passwords
Author: Simon Willison
License: Apache License, Version 2.0
Project-URL: Issues, https://github.com/simonw/datasette-auth-passwords/issues
Project-URL: CI, https://github.com/simonw/datasette-auth-passwords/actions
Project-URL: Changelog, https://github.com/simonw/datasette-auth-passwords/releases
Requires-Dist: datasette >=0.59
Provides-Extra: test
Requires-Dist: pytest ; extra == 'test'
Requires-Dist: pytest-asyncio ; extra == 'test'
Requires-Dist: httpx ; extra == 'test'
